sql2csv/__init__.py
sql2csv/__main__.py
sql2csv/sql2csv.py
sql2csv-1.3.dist-info/LICENSE
sql2csv-1.3.dist-info/METADATA
sql2csv-1.3.dist-info/WHEEL
sql2csv-1.3.dist-info/entry_points.txt
sql2csv-1.3.dist-info/top_level.txt
sql2csv-1.3.dist-info/RECORD
