Metadata-Version: 2.1
Name: sql2csv
Version: 1.3
Summary: Run MySQL and PostgreSQL queries and store result in CSV
Home-page: https://github.com/gabfl/sql2csv
Author: Gabriel Bordeaux
Author-email: pypi@gab.lc
License: MIT
Platform: UNKNOWN
Classifier: Topic :: Database
Classifier: Topic :: Database :: Database Engines/Servers
Classifier: License :: OSI Approved :: MIT License
Classifier: Operating System :: MacOS
Classifier: Operating System :: POSIX :: Linux
Classifier: Natural Language :: English
Classifier: Programming Language :: Python :: 3
Classifier: Programming Language :: Python
Classifier: Development Status :: 4 - Beta
Requires-Dist: argparse
Requires-Dist: PyYAML
Requires-Dist: pymysql
Requires-Dist: psycopg2-binary
